LICENSE
MANIFEST.in
README.rst
requirements.txt
setup.py
test_apod.py
apod_wallpaper/OpenSans-Regular.ttf
apod_wallpaper/__init__.py
apod_wallpaper/apod.py
apod_wallpaper/date_utils.py
apod_wallpaper/file_utils.py
apod_wallpaper/watermark.py
apod_wallpaper.egg-info/PKG-INFO
apod_wallpaper.egg-info/SOURCES.txt
apod_wallpaper.egg-info/dependency_links.txt
apod_wallpaper.egg-info/not-zip-safe
apod_wallpaper.egg-info/requires.txt
apod_wallpaper.egg-info/top_level.txt