Metadata-Version: 1.1
Name: apod-wallpaper
Version: 1.1.2
Summary: NASA APOD wallpaper download
Home-page: https://github.com/jasonh-n-austin/python-apod-wallpaper
Author: Jason Harmon
Author-email: jason.harmon@gmail.com
License: Apache 2.0
Platform: any
Classifier: Development Status :: 4 - Beta
Classifier: Intended Audience :: Developers
Classifier: Intended Audience :: End Users/Desktop
Classifier: Natural Language :: English
Classifier: License :: OSI Approved :: Apache Software License
Classifier: Operating System :: OS Independent
Classifier: Programming Language :: Python
Classifier: Programming Language :: Python :: 3
Classifier: Programming Language :: Python :: 3.3
Classifier: Programming Language :: Python :: 3.4
Classifier: Programming Language :: Python :: 3.5
Classifier: Topic :: Utilities
Classifier: Topic :: Software Development :: Libraries :: Python Modules
